{"dependencies":[{"name":"apollo-client","loc":{"line":4,"column":35}},{"name":"bs-platform/lib/js/js_null_undefined.js","loc":{"line":5,"column":35}},{"name":"./graphql-types/ReasonApolloQuery.bs.js","loc":{"line":6,"column":35}},{"name":"./graphql-types/ReasonApolloMutation.bs.js","loc":{"line":7,"column":35}}],"generated":{"js":"\"use strict\";var e=require(\"apollo-client\"),o=require(\"bs-platform/lib/js/js_null_undefined.js\"),r=require(\"./graphql-types/ReasonApolloQuery.bs.js\"),t=require(\"./graphql-types/ReasonApolloMutation.bs.js\");function l(r,t,l,n,s,i,a){return new e.ApolloClient({link:t,cache:r,ssrMode:o.from_opt(l),ssrForceFetchDelay:o.from_opt(n),connectToDevTools:o.from_opt(s),queryDeduplication:o.from_opt(i)})}function n(e){var o=e[0];return[o,r.QueryFactory([o]),t.MutationFactory([o])]}exports.createApolloClient=l,exports.CreateClient=n;"},"hash":"cef3f7d1020ea7a514ed53f9b8cb3db6","cacheData":{"env":{}}}