{"dependencies":[{"name":"bs-platform/lib/js/block.js","loc":{"line":4,"column":36}},{"name":"../../niceComponents.bs.js","loc":{"line":5,"column":36}}],"generated":{"js":"\"use strict\";var e=require(\"bs-platform/lib/js/block.js\"),_=require(\"../../niceComponents.bs.js\"),s=_.code([\"Code\"],[e.__(49,[e.__(4,[\"f8faff\"])]),e.__(0,[1]),e.__(18,[e.__(2,[1])]),e.__(55,[e.__(0,[3])])]),o=s[0],r=s[1],t=s[2];exports.className=o,exports.component=r,exports.make=t;"},"hash":"6b544e03f7b51db610cf25bb66b4f5bd","cacheData":{"env":{}}}